[
	  {
		      "number": 51,
		          "name": "Bobélix",
			      "description": "7a",
			          "quotation": "e",
				      "equipment": ""
				        },
					  {
						      "number": 52,
						          "name": "Dégonflé",
							      "description": "6b",
							          "quotation": "e",
								      "equipment": ""
								        },
									  {
										      "number": 53,
										          "name": "Gruyères",
											      "description": 4,
											          "quotation": "e",
												      "equipment": ""
												        },
													  {
														      "number": 54,
														          "name": "Gouda",
															      "description": 3,
															          "quotation": "e",
																      "equipment": ""
																        },
																	  {
																		      "number": 55,
																		          "name": "Mimolette",
																			      "description": 3,
																			          "quotation": "e",
																				      "equipment": ""
																				        },
																					  {
																						      "number": 56,
																						          "name": "Sterno-cléido-mastodien",
																							      "description": "6a",
																							          "quotation": "e",
																								      "equipment": ""
																								        }
]
